pyrregular/__init__.py
pyrregular/_version.py
pyrregular/accessor.py
pyrregular/backend.py
pyrregular/conversion_utils.py
pyrregular/data_utils.py
pyrregular/describe.py
pyrregular/io_utils.py
pyrregular/reader_interface.py
pyrregular/registry.txt
pyrregular/repository.py
pyrregular/uea_ucr_datasets.py
pyrregular/datasets/__init__.py
pyrregular/datasets/abf.py
pyrregular/datasets/ais.py
pyrregular/datasets/animals.py
pyrregular/datasets/combined_trajectories.py
pyrregular/datasets/garment.py
pyrregular/datasets/geolife.py
pyrregular/datasets/geolife_supervised.py
pyrregular/datasets/ldfpa.py
pyrregular/datasets/mimic3.py
pyrregular/datasets/pamap2.py
pyrregular/datasets/physionet2012.py
pyrregular/datasets/physionet2019.py
pyrregular/datasets/seabirds.py
pyrregular/datasets/t_drive.py
pyrregular/datasets/taxi.py
pyrregular/datasets/vehicles.py
pyrregular/dev/__init__.py
pyrregular/dev/repository_dev.py
pyrregular/models/__init__.py
pyrregular/models/borf.py
pyrregular/models/brits.py
pyrregular/models/grud.py
pyrregular/models/knn.py
pyrregular/models/lgbm.py
pyrregular/models/ncde.py
pyrregular/models/nodes.py
pyrregular/models/raindrop.py
pyrregular/models/ridge_cv.py
pyrregular/models/rifc.py
pyrregular/models/rocket.py
pyrregular/models/saits.py
pyrregular/models/svm.py
pyrregular/models/timesnet.py
pyrregular/wrappers/__init__.py
pyrregular/wrappers/pypots_wrapper.py
pyrregular/wrappers/tslearn_wrapper.py
tests/__init__.py
tests/constants.py
tests/test_dataset_loading.py
tests/_deprecated/__init__.py
tests/_deprecated/test_dataset_conversion.py
tests/_deprecated/test_dataset_sanity.py
tests/_deprecated/utils.py
pyrregular-0.1.10.dist-info/METADATA
pyrregular-0.1.10.dist-info/WHEEL
pyrregular-0.1.10.dist-info/entry_points.txt
pyrregular-0.1.10.dist-info/top_level.txt
pyrregular-0.1.10.dist-info/RECORD
