Metadata-Version: 2.4
Name: pyrregular
Version: 0.1.10
Summary: Irregular time series made easy
Author: Francesco Spinnato, Cristiano Landi
Author-email: francesco.spinnato@di.unipi.it
Classifier: Programming Language :: Python :: 3
Classifier: Programming Language :: Python :: 3.9
Classifier: Programming Language :: Python :: 3.9
Classifier: Programming Language :: Python :: 3.10
Classifier: Programming Language :: Python :: 3.11
Classifier: Programming Language :: Python :: 3.12
Requires-Python: >=3.9
Requires-Dist: awkward
Requires-Dist: numpy
Requires-Dist: pandas
Requires-Dist: xarray
Requires-Dist: sparse<=0.15.4
Requires-Dist: h5py
Requires-Dist: pyarrow
Requires-Dist: pooch
Requires-Dist: tqdm
Requires-Dist: scikit-learn
Requires-Dist: pyyaml
Provides-Extra: dev
Requires-Dist: black; extra == "dev"
Requires-Dist: mypy; extra == "dev"
Requires-Dist: pre-commit; extra == "dev"
Requires-Dist: pytest; extra == "dev"
Requires-Dist: pytest-cov; extra == "dev"
Provides-Extra: docs
Requires-Dist: sphinx>=6.0; extra == "docs"
Requires-Dist: myst-parser; extra == "docs"
Requires-Dist: nbsphinx; extra == "docs"
Requires-Dist: sphinx-autodoc-typehints; extra == "docs"
Requires-Dist: sphinxcontrib-napoleon; extra == "docs"
Requires-Dist: ipykernel; extra == "docs"
Requires-Dist: nbconvert; extra == "docs"
Requires-Dist: snowballstemmer<3.0.0; extra == "docs"
Provides-Extra: test
Requires-Dist: pytest; extra == "test"
Requires-Dist: pytest-cov; extra == "test"
Provides-Extra: notebooks
Requires-Dist: notebook; extra == "notebooks"
Provides-Extra: models
Requires-Dist: lightgbm; extra == "models"
Requires-Dist: sktime; extra == "models"
Requires-Dist: aeon; extra == "models"
Requires-Dist: tslearn; extra == "models"
Requires-Dist: pypots; extra == "models"
Requires-Dist: jax; extra == "models"
Requires-Dist: equinox; extra == "models"
Requires-Dist: optax; extra == "models"
Requires-Dist: diffrax; extra == "models"
